commonlisteners/__init__.py
commonlisteners/interfaces.py
commonlisteners/listeners.py
commonlisteners-0.0.7.dist-info/METADATA
commonlisteners-0.0.7.dist-info/WHEEL
commonlisteners-0.0.7.dist-info/licenses/LICENSE
commonlisteners-0.0.7.dist-info/RECORD
